rinoh_typeface_urwdingbats/COPYING
rinoh_typeface_urwdingbats/LICENSE
rinoh_typeface_urwdingbats/__init__.py
rinoh_typeface_urwdingbats/d050000l.afm
rinoh_typeface_urwdingbats/d050000l.pfb
rinoh_typeface_urwdingbats-0.1.1.dist-info/DESCRIPTION.rst
rinoh_typeface_urwdingbats-0.1.1.dist-info/METADATA
rinoh_typeface_urwdingbats-0.1.1.dist-info/RECORD
rinoh_typeface_urwdingbats-0.1.1.dist-info/WHEEL
rinoh_typeface_urwdingbats-0.1.1.dist-info/entry_points.txt
rinoh_typeface_urwdingbats-0.1.1.dist-info/metadata.json
rinoh_typeface_urwdingbats-0.1.1.dist-info/top_level.txt
