Metadata-Version: 2.0
Name: rinoh-typeface-urwdingbats
Version: 0.1.1
Summary: URW Dingbats typeface
Home-page: https://github.com/brechtm/rinoh-typeface-urwdingbats
Author: Brecht Machiels
Author-email: brecht@mos6581.org
License: GNU AGPL v3
Keywords: type1 font
Platform: UNKNOWN
Classifier: Intended Audience :: Developers
Classifier: Intended Audience :: End Users/Desktop
Classifier: Operating System :: OS Independent
Classifier: License :: OSI Approved :: GNU Affero General Public License v3
Classifier: Programming Language :: Python
Classifier: Programming Language :: Python :: 3
Classifier: Topic :: Text Processing :: Fonts
Requires-Dist: rinohtype
